pybiblionet/bibliometric_analysis/charts.py
pybiblionet/bibliometric_analysis/charts_network.py
pybiblionet/bibliometric_analysis/core.py
pybiblionet/openalex/core.py
pybiblionet/openalex/utils.py
pybiblionet/tests/__init__.py
pybiblionet/tests/stisitiche cluster.py
pybiblionet/tests/test_charts.py
pybiblionet/tests/test_network_analysis.py
pybiblionet/tests/test_openalex.py
pybiblionet/tests/text_pybibx.py
pybiblionet-1.0.5.dist-info/licenses/LICENSE
pybiblionet-1.0.5.dist-info/METADATA
pybiblionet-1.0.5.dist-info/WHEEL
pybiblionet-1.0.5.dist-info/top_level.txt
pybiblionet-1.0.5.dist-info/RECORD
