Metadata-Version: 2.4
Name: pybiblionet
Version: 1.0.5
Summary: PyBiblioNet is a Python library for performing network-based bibliometrics
License:                     GNU GENERAL PUBLIC LICENSE
Project-URL: Homepage, https://github.com/mirkolai/pybiblionet
Project-URL: Repository, https://github.com/mirkolai/pybiblionet
Project-URL: Issues, https://github.com/mirkolai/pybiblionet/issues
Project-URL: Documentation, https://github.com/mirkolai/pybiblionet#readme
License-File: LICENSE
Requires-Dist: infomap==2.8.0
Requires-Dist: keybert==0.9.0
Requires-Dist: matplotlib==3.10.5
Requires-Dist: networkx==3.5
Requires-Dist: numpy==2.3.2
Requires-Dist: pandas==2.3.1
Requires-Dist: python_igraph==0.11.9
Requires-Dist: Requests==2.32.4
Requires-Dist: scikit_learn==1.7.1
Requires-Dist: seaborn==0.13.2
Requires-Dist: tqdm==4.67.1
Requires-Dist: python-louvain==0.16
Requires-Dist: spacy>=3.8.7
Dynamic: license-file
